DistributedML/__init__.py
DistributedML/core.py
DistributedML/utils.py
distributed_ml-0.1.0.dist-info/LICENSE
distributed_ml-0.1.0.dist-info/METADATA
distributed_ml-0.1.0.dist-info/WHEEL
distributed_ml-0.1.0.dist-info/top_level.txt
distributed_ml-0.1.0.dist-info/RECORD
