Metadata-Version: 2.2
Name: distributed-ml
Version: 0.1.0
Summary: A package for training models via API calls
Home-page: https://github.com/sumitraut7/CS230-distributed-machine-learning
Author: Your Name
Author-email: Sumit Raut <sumitcraut@gmail.com>
Requires-Python: >=3.6
License-File: LICENSE
Requires-Dist: requests
Dynamic: author
Dynamic: home-page
Dynamic: requires-python
